PicImageSearch/__init__.py
PicImageSearch/constants.py
PicImageSearch/exceptions.py
PicImageSearch/network.py
PicImageSearch/sync.py
PicImageSearch/types.py
PicImageSearch/utils.py
PicImageSearch/engines/__init__.py
PicImageSearch/engines/anime_trace.py
PicImageSearch/engines/ascii2d.py
PicImageSearch/engines/baidu.py
PicImageSearch/engines/base.py
PicImageSearch/engines/bing.py
PicImageSearch/engines/copyseeker.py
PicImageSearch/engines/ehentai.py
PicImageSearch/engines/google.py
PicImageSearch/engines/google_lens.py
PicImageSearch/engines/iqdb.py
PicImageSearch/engines/lenso.py
PicImageSearch/engines/saucenao.py
PicImageSearch/engines/tineye.py
PicImageSearch/engines/tracemoe.py
PicImageSearch/engines/yandex.py
PicImageSearch/model/__init__.py
PicImageSearch/model/anime_trace.py
PicImageSearch/model/ascii2d.py
PicImageSearch/model/baidu.py
PicImageSearch/model/base.py
PicImageSearch/model/bing.py
PicImageSearch/model/copyseeker.py
PicImageSearch/model/ehentai.py
PicImageSearch/model/google.py
PicImageSearch/model/google_lens.py
PicImageSearch/model/iqdb.py
PicImageSearch/model/lenso.py
PicImageSearch/model/saucenao.py
PicImageSearch/model/tineye.py
PicImageSearch/model/tracemoe.py
PicImageSearch/model/yandex.py
picimagesearch-3.12.11.dist-info/METADATA
picimagesearch-3.12.11.dist-info/WHEEL
picimagesearch-3.12.11.dist-info/licenses/LICENSE
picimagesearch-3.12.11.dist-info/RECORD
