Metadata-Version: 2.4
Name: PicImageSearch
Version: 3.12.11
Summary: PicImageSearch - Aggregator for Reverse Image Search APIs
Project-URL: homepage, https://github.com/kitUIN/PicImageSearch
Project-URL: repository, https://github.com/kitUIN/PicImageSearch
Author-email: kitUIN <kulujun@gmail.com>
Maintainer: lleans, chinoll, NekoAria
Maintainer-email: kitUIN <kulujun@gmail.com>
License: MIT
License-File: LICENSE
Keywords: animetrace,ascii2d,baidu,bing,copyseeker,e-hentai,google,google-lens,iqdb,saucenao,tineye,tracemoe,yandex
Requires-Python: >=3.9
Requires-Dist: httpx[http2]>=0.28.1
Requires-Dist: lxml<6.0.0,>=5.4.0
Requires-Dist: pyquery>=2.0.1
Provides-Extra: socks
Requires-Dist: socksio>=1.0.0; extra == 'socks'
